ufload3/__init__.py
ufload3/cloud.py
ufload3/db.py
ufload3/test_cloud.py
ufload3/test_db.py
ufload3/webdav.py
ufload3/cli/__init__.py
ufload3/cli/main.py
ufload3/cli/test_main.py
ufload3-2.2.dist-info/licenses/LICENSE
ufload3-2.2.dist-info/METADATA
ufload3-2.2.dist-info/WHEEL
ufload3-2.2.dist-info/entry_points.txt
ufload3-2.2.dist-info/top_level.txt
ufload3-2.2.dist-info/RECORD
