Metadata-Version: 2.4
Name: ufload3
Version: 2.2
Summary: UniField  python3 loader
Author: MSF
Project-URL: Homepage, https://github.com/Unifield/ufload3
Classifier: Programming Language :: Python :: 3
Classifier: Development Status :: 3 - Alpha
Classifier: License :: OSI Approved :: MIT License
Classifier: Operating System :: OS Independent
Requires-Python: >=3.10
License-File: LICENSE
Requires-Dist: Office365-REST-Python-Client==2.6.2
Dynamic: license-file
